MANIFEST.in
README.md
setup.py
blender/__init__.py
blender/bpy.so
blender.egg-info/PKG-INFO
blender.egg-info/SOURCES.txt
blender.egg-info/dependency_links.txt
blender.egg-info/top_level.txt
blender/2.79/scripts/addons/add_curve_ivygen.py
blender/2.79/scripts/addons/animation_add_corrective_shape_key.py
blender/2.79/scripts/addons/animation_animall.py
blender/2.79/scripts/addons/bone_selection_sets.py
blender/2.79/scripts/addons/camera_dolly_crane_rigs.py
blender/2.79/scripts/addons/camera_turnaround.py
blender/2.79/scripts/addons/curve_simplify.py
blender/2.79/scripts/addons/development_api_navigator.py
blender/2.79/scripts/addons/development_edit_operator.py
blender/2.79/scripts/addons/development_icon_get.py
blender/2.79/scripts/addons/development_iskeyfree.py
blender/2.79/scripts/addons/development_ui_classes.py
blender/2.79/scripts/addons/game_engine_publishing.py
blender/2.79/scripts/addons/game_engine_save_as_runtime.py
blender/2.79/scripts/addons/io_anim_camera.py
blender/2.79/scripts/addons/io_export_after_effects.py
blender/2.79/scripts/addons/io_export_paper_model.py
blender/2.79/scripts/addons/io_export_pc2.py
blender/2.79/scripts/addons/io_export_unreal_psk_psa.py
blender/2.79/scripts/addons/io_import_gimp_image_to_scene.py
blender/2.79/scripts/addons/io_import_images_as_planes.py
blender/2.79/scripts/addons/io_import_scene_lwo.py
blender/2.79/scripts/addons/io_import_scene_unreal_psa_psk.py
blender/2.79/scripts/addons/lighting_dynamic_sky.py
blender/2.79/scripts/addons/mesh_auto_mirror.py
blender/2.79/scripts/addons/mesh_bsurfaces.py
blender/2.79/scripts/addons/mesh_carver.py
blender/2.79/scripts/addons/mesh_custom_normals_tools.py
blender/2.79/scripts/addons/mesh_f2.py
blender/2.79/scripts/addons/mesh_looptools.py
blender/2.79/scripts/addons/mesh_relax.py
blender/2.79/scripts/addons/mesh_snap_utilities_line.py
blender/2.79/scripts/addons/node_wrangler.py
blender/2.79/scripts/addons/object_animrenderbake.py
blender/2.79/scripts/addons/object_boolean_tools.py
blender/2.79/scripts/addons/object_cloud_gen.py
blender/2.79/scripts/addons/object_edit_linked.py
