Metadata-Version: 1.0
Name: blender
Version: 1.3
Summary: Pre-built Blender 2.79 as a python3.5 module bpy for linux.
Home-page: https://github.com/uzairakbar/blender/archive/v1.3.tar.gz
Author: Uzair Akbar
Author-email: uzairakbar@outlook.com
License: UNKNOWN
Platform: UNKNOWN
